httpx_ntlm/__init__.py
httpx_ntlm/httpx_ntlm.py
httpx_ntlm_fixed-1.4.1.dist-info/licenses/LICENSE
httpx_ntlm_fixed-1.4.1.dist-info/METADATA
httpx_ntlm_fixed-1.4.1.dist-info/WHEEL
httpx_ntlm_fixed-1.4.1.dist-info/top_level.txt
httpx_ntlm_fixed-1.4.1.dist-info/RECORD
