Metadata-Version: 2.4
Name: httpx_ntlm_fixed
Version: 1.4.1
Summary: This package allows for HTTP NTLM authentication using the HTTPX library. Fork of httpx_ntlm with fixes.
Home-page: https://github.com/LogicDaemon/httpx-ntlm
Author: LogicDaemon
Author-email: pub-pypi@logicdaemon.ru
License: ISC
Classifier: Development Status :: 4 - Beta
Classifier: Intended Audience :: Developers
Classifier: Programming Language :: Python
Classifier: Programming Language :: Python :: 3.6
Classifier: Programming Language :: Python :: 3.7
Classifier: Programming Language :: Python :: 3.8
Classifier: Programming Language :: Python :: 3.9
Classifier: Programming Language :: Python :: 3.10
Classifier: Programming Language :: Python :: 3.11
Classifier: Programming Language :: Python :: 3.12
Classifier: Programming Language :: Python :: 3.13
Classifier: Programming Language :: Python :: 3.14
Classifier: License :: OSI Approved :: ISC License (ISCL)
Provides: httpx_ntlm
License-File: LICENSE
Requires-Dist: httpx>=0.24
Requires-Dist: pyspnego>=0.3
Dynamic: author
Dynamic: author-email
Dynamic: classifier
Dynamic: description
Dynamic: description-content-type
Dynamic: home-page
Dynamic: license
Dynamic: license-file
Dynamic: provides
Dynamic: requires-dist
Dynamic: summary
